neural_mcp/__init__.py
neural_mcp/server.py
scicomp_neural_mcp-0.1.6.dist-info/METADATA
scicomp_neural_mcp-0.1.6.dist-info/WHEEL
scicomp_neural_mcp-0.1.6.dist-info/entry_points.txt
scicomp_neural_mcp-0.1.6.dist-info/RECORD
