Metadata-Version: 2.4
Name: scicomp-neural-mcp
Version: 0.1.6
Summary: MCP server for neural network training and experimentation
Project-URL: Homepage, https://github.com/andylbrummer/math-mcp
Project-URL: Documentation, https://andylbrummer.github.io/math-mcp/api/neural-mcp
Project-URL: Repository, https://github.com/andylbrummer/math-mcp
Author-email: Andy Brummer <andy@example.com>
License-Expression: MIT
Keywords: deep-learning,mcp,model-context-protocol,network,neural,pytorch,training
Classifier: Development Status :: 4 - Beta
Classifier: Intended Audience :: Developers
Classifier: Intended Audience :: Science/Research
Classifier: License :: OSI Approved :: MIT License
Classifier: Programming Language :: Python :: 3
Classifier: Programming Language :: Python :: 3.11
Classifier: Programming Language :: Python :: 3.12
Classifier: Topic :: Scientific/Engineering :: Artificial Intelligence
Requires-Python: >=3.11
Requires-Dist: matplotlib>=3.8.0
Requires-Dist: mcp>=1.0.0
Requires-Dist: numpy>=1.26.0
Requires-Dist: scicomp-compute-core>=0.1.6
Requires-Dist: scicomp-mcp-common>=0.1.6
Requires-Dist: torch>=2.1.0
Requires-Dist: torchvision>=0.16.0
